leomusiclib/__init__.py
leomusiclib/chords.py
leomusiclib/intervals.py
leomusiclib/notetocode.py
leomusiclib-0.99.dist-info/LICENSE
leomusiclib-0.99.dist-info/METADATA
leomusiclib-0.99.dist-info/WHEEL
leomusiclib-0.99.dist-info/top_level.txt
leomusiclib-0.99.dist-info/RECORD
