Metadata-Version: 2.1
Name: leomusiclib
Version: 0.99
Summary: A package for working with music, intervals, chords
Author-email: Lev Savosh <lev.savosh11@mail.ru>
Project-URL: Homepage, https://github.com/pypa/musiclib
Classifier: Programming Language :: Python :: 3
Classifier: License :: OSI Approved :: MIT License
Classifier: Operating System :: OS Independent
Requires-Python: >=3.10
License-File: LICENSE
